<annotation>
	<folder>Potato___healthy</folder>
	<filename>1f9870b3-899e-46fb-98c9-cfc2ce92895b___RS_HL 1816_new30degFlipLR.JPG</filename>
	<path>/home/student/Downloads/archive/new plant diseases dataset(augmented)/New Plant Diseases Dataset(Augmented)/train/Potato___healthy/1f9870b3-899e-46fb-98c9-cfc2ce92895b___RS_HL 1816_new30degFlipLR.JPG</path>
	<source>
		<database>Unknown</database>
	</source>
	<size>
		<width>256</width>
		<height>256</height>
		<depth>3</depth>
	</size>
	<segmented>0</segmented>
	<object>
		<name>Healthy_leaf</name>
		<pose>Unspecified</pose>
		<truncated>0</truncated>
		<difficult>0</difficult>
		<bndbox>
			<xmin>57</xmin>
			<ymin>19</ymin>
			<xmax>224</xmax>
			<ymax>246</ymax>
		</bndbox>
	</object>
</annotation>
