<annotation>
	<folder>Potato___Early_blight</folder>
	<filename>51f59871-72dc-490c-a550-9e7869142284___RS_Early.B 7224_180deg.JPG</filename>
	<path>/home/student/Downloads/archive/New Plant Diseases Dataset(Augmented)/New Plant Diseases Dataset(Augmented)/train/Potato___Early_blight/51f59871-72dc-490c-a550-9e7869142284___RS_Early.B 7224_180deg.JPG</path>
	<source>
		<database>Unknown</database>
	</source>
	<size>
		<width>256</width>
		<height>256</height>
		<depth>3</depth>
	</size>
	<segmented>0</segmented>
	<object>
		<name>Early_blight</name>
		<pose>Unspecified</pose>
		<truncated>0</truncated>
		<difficult>0</difficult>
		<bndbox>
			<xmin>10</xmin>
			<ymin>13</ymin>
			<xmax>248</xmax>
			<ymax>244</ymax>
		</bndbox>
	</object>
</annotation>
